sawyer_cz.py
sawyer_cz-0.3.4.dist-info/licenses/LICENSE.txt
sawyer_cz-0.3.4.dist-info/METADATA
sawyer_cz-0.3.4.dist-info/WHEEL
sawyer_cz-0.3.4.dist-info/entry_points.txt
sawyer_cz-0.3.4.dist-info/top_level.txt
sawyer_cz-0.3.4.dist-info/RECORD
