Metadata-Version: 2.4
Name: sawyer-cz
Version: 0.3.4
Summary: A custom plugin for commitizen
License: MIT License
Keywords: commitizen,conventional-commits,cz
Classifier: Development Status :: 3 - Alpha
Classifier: License :: OSI Approved :: MIT License
Classifier: Programming Language :: Python :: 3
Classifier: Programming Language :: Python :: 3 :: Only
Requires-Python: >=3.10
License-File: LICENSE.txt
Requires-Dist: commitizen>=4.12.1
Dynamic: license-file
